Metadata-Version: 2.4
Name: create-django-inertia
Version: 1.0.2
Summary: A CLI tool to quickly scaffold Django + Inertia.js projects with React or Vue
Home-page: https://github.com/TITANHACKY/create-django-inertia
Author: Django Inertia Starter Team
Author-email: Django Inertia Starter Team <contact@create-django-inertia.com>
License: MIT
Project-URL: Homepage, https://github.com/TITANHACKY/create-django-inertia
Project-URL: Bug Reports, https://github.com/TITANHACKY/create-django-inertia/issues
Project-URL: Source, https://github.com/TITANHACKY/create-django-inertia
Project-URL: Documentation, https://github.com/TITANHACKY/create-django-inertia#readme
Keywords: django,inertia,inertiajs,react,vue,typescript,javascript,scaffolding,cli,vite,tailwind
Classifier: Development Status :: 4 - Beta
Classifier: Intended Audience :: Developers
Classifier: Topic :: Software Development :: Code Generators
Classifier: Topic :: Internet :: WWW/HTTP :: Dynamic Content
Classifier: Programming Language :: Python :: 3
Classifier: Programming Language :: Python :: 3.8
Classifier: Programming Language :: Python :: 3.9
Classifier: Programming Language :: Python :: 3.10
Classifier: Programming Language :: Python :: 3.11
Classifier: Programming Language :: Python :: 3.12
Classifier: Framework :: Django
Classifier: Framework :: Django :: 4.0
Classifier: Framework :: Django :: 4.1
Classifier: Framework :: Django :: 4.2
Classifier: Framework :: Django :: 5.0
Classifier: Operating System :: OS Independent
Requires-Python: >=3.8
License-File: LICENSE
Requires-Dist: click>=8.0.0
Requires-Dist: jinja2>=3.0.0
Requires-Dist: colorama>=0.4.4
Requires-Dist: requests>=2.25.0
Dynamic: author
Dynamic: home-page
Dynamic: license-file
Dynamic: requires-python
